QtTheme/__init__.py
QtTheme/PyQt5/__init__.py
QtTheme/PyQt5/resource.py
QtTheme/PyQt6/__init__.py
QtTheme/PyQt6/resource.py
QtTheme/PySide2/__init__.py
QtTheme/PySide2/resource.py
QtTheme/PySide6/__init__.py
QtTheme/PySide6/resource.py
qttheme-1.0.2.dist-info/METADATA
qttheme-1.0.2.dist-info/WHEEL
qttheme-1.0.2.dist-info/licenses/LICENSE
qttheme-1.0.2.dist-info/RECORD
