Metadata-Version: 2.4
Name: QtTheme
Version: 1.0.2
Summary: Qt theme in pure qss
Project-URL: Homepage, https://github.com/hubenchang0515/QtTheme
Project-URL: Issues, https://github.com/hubenchang0515/QtTheme/issues
Author-email: Plan C <hubenchang0515@outlook.com>
License-Expression: AGPL-3.0-or-later
License-File: LICENSE
Classifier: Operating System :: OS Independent
Classifier: Programming Language :: Python :: 3
Requires-Python: >=3.8
